models/Address.py
models/AddressCSV.py
models/RomanInteger.py
models/__init__.py
presets/__init__.py
presets/clear_characters.py
presets/fias_types.py
tests/__init__.py
tests/test_address.py
tests/test_roman_integer.py
lod_dedovschina_sber-1.0.4.dist-info/METADATA
lod_dedovschina_sber-1.0.4.dist-info/WHEEL
lod_dedovschina_sber-1.0.4.dist-info/top_level.txt
lod_dedovschina_sber-1.0.4.dist-info/RECORD
