Metadata-Version: 2.1
Name: lod-dedovschina-sber
Version: 1.0.4
Summary: Исходный код задания для кейса от Сбербанка
Home-page: https://github.com/NtZyr/digital-hack-sber
Author: Дедовщина
License: UNKNOWN
Platform: UNKNOWN
Requires-Python: >=3.6
